Metadata-Version: 2.1
Name: palg
Version: 0.0.1
Summary: print/打印
Home-page: https://alggfzslt.freeflarum.com/
Author: algfwq
Author-email: 3104374883@qq.com
License: MIT License
Platform: UNKNOWN
